huaweicloudsdkdis/__init__.py
huaweicloudsdkdis/v2/__init__.py
huaweicloudsdkdis/v2/dis_async_client.py
huaweicloudsdkdis/v2/dis_client.py
huaweicloudsdkdis/v2/model/__init__.py
huaweicloudsdkdis/v2/model/batch_create_tags_req.py
huaweicloudsdkdis/v2/model/batch_create_tags_request.py
huaweicloudsdkdis/v2/model/batch_create_tags_response.py
huaweicloudsdkdis/v2/model/batch_delete_tags_req.py
huaweicloudsdkdis/v2/model/batch_delete_tags_request.py
huaweicloudsdkdis/v2/model/batch_delete_tags_response.py
huaweicloudsdkdis/v2/model/batch_start_transfer_task_req.py
huaweicloudsdkdis/v2/model/batch_start_transfer_task_request.py
huaweicloudsdkdis/v2/model/batch_start_transfer_task_response.py
huaweicloudsdkdis/v2/model/batch_stop_transfer_task_req.py
huaweicloudsdkdis/v2/model/batch_stop_transfer_task_request.py
huaweicloudsdkdis/v2/model/batch_stop_transfer_task_response.py
huaweicloudsdkdis/v2/model/batch_transfer_task.py
huaweicloudsdkdis/v2/model/cloudtable_destination_descriptor_request.py
huaweicloudsdkdis/v2/model/cloudtable_schema.py
huaweicloudsdkdis/v2/model/column.py
huaweicloudsdkdis/v2/model/commit_checkpoint_req.py
huaweicloudsdkdis/v2/model/commit_checkpoint_request.py
huaweicloudsdkdis/v2/model/commit_checkpoint_response.py
huaweicloudsdkdis/v2/model/common_destination_descriptor.py
huaweicloudsdkdis/v2/model/consume_records_request.py
huaweicloudsdkdis/v2/model/consume_records_response.py
huaweicloudsdkdis/v2/model/create_app_req.py
huaweicloudsdkdis/v2/model/create_app_request.py
huaweicloudsdkdis/v2/model/create_app_response.py
huaweicloudsdkdis/v2/model/create_obs_transfer_task_request.py
huaweicloudsdkdis/v2/model/create_obs_transfer_task_response.py
huaweicloudsdkdis/v2/model/create_stream_req.py
huaweicloudsdkdis/v2/model/create_stream_request.py
huaweicloudsdkdis/v2/model/create_stream_response.py
huaweicloudsdkdis/v2/model/create_tag_req.py
huaweicloudsdkdis/v2/model/create_tag_request.py
huaweicloudsdkdis/v2/model/create_tag_response.py
huaweicloudsdkdis-3.1.184.dist-info/METADATA
huaweicloudsdkdis-3.1.184.dist-info/WHEEL
huaweicloudsdkdis-3.1.184.dist-info/licenses/LICENSE
huaweicloudsdkdis-3.1.184.dist-info/RECORD
